pso_optimizer/__init__.py
pso_optimizer/hyperparameter_mappings.py
pso_optimizer/pso.py
pso_optimizer-1.0.1.dist-info/METADATA
pso_optimizer-1.0.1.dist-info/WHEEL
pso_optimizer-1.0.1.dist-info/top_level.txt
pso_optimizer-1.0.1.dist-info/RECORD
